iam_principal_enumerator/__init__.py
iam_principal_enumerator/aws/__init__.py
iam_principal_enumerator/aws/helpers.py
iam_principal_enumerator/aws/iam.py
iam_principal_enumerator/aws/sts.py
iam_principal_enumerator/main.py
iam_principal_enumerator/util/__init__.py
iam_principal_enumerator-0.1.1.dist-info/LICENSE
iam_principal_enumerator-0.1.1.dist-info/METADATA
iam_principal_enumerator-0.1.1.dist-info/WHEEL
iam_principal_enumerator-0.1.1.dist-info/entry_points.txt
iam_principal_enumerator-0.1.1.dist-info/RECORD
