Metadata-Version: 2.1
Name: iam-principal-enumerator
Version: 0.1.1
Summary: CLI application that performs unauthenticated IAM principal enumeration against a target AWS account.
Home-page: https://github.com/f0xtek/iam-principal-enumerator
License: MIT
Author: Luke Anderson
Author-email: landerson61@gmail.com
Requires-Python: >=3.11,<4.0
Classifier: License :: OSI Approved :: MIT License
Classifier: Programming Language :: Python :: 3
Classifier: Programming Language :: Python :: 3.11
Classifier: Programming Language :: Python :: 3.12
Classifier: Programming Language :: Python :: 3.13
Requires-Dist: boto3 (>=1.35.76,<2.0.0)
Requires-Dist: loguru (>=0.7.2,<0.8.0)
Project-URL: Repository, https://github.com/f0xtek/iam-principal-enumerator
